social_core/__init__.py
social_core/actions.py
social_core/exceptions.py
social_core/storage.py
social_core/store.py
social_core/strategy.py
social_core/utils.py
social_core/backends/__init__.py
social_core/backends/amazon.py
social_core/backends/angel.py
social_core/backends/aol.py
social_core/backends/appsfuel.py
social_core/backends/arcgis.py
social_core/backends/asana.py
social_core/backends/azuread.py
social_core/backends/azuread_b2c.py
social_core/backends/azuread_tenant.py
social_core/backends/base.py
social_core/backends/battlenet.py
social_core/backends/beats.py
social_core/backends/behance.py
social_core/backends/belgiumeid.py
social_core/backends/bitbucket.py
social_core/backends/box.py
social_core/backends/bungie.py
social_core/backends/changetip.py
social_core/backends/chatwork.py
social_core/backends/classlink.py
social_core/backends/clef.py
social_core/backends/coding.py
social_core/backends/coinbase.py
social_core/backends/coursera.py
social_core/backends/dailymotion.py
social_core/backends/deezer.py
social_core/backends/digitalocean.py
social_core/backends/disqus.py
social_core/backends/docker.py
social_core/backends/douban.py
social_core/backends/dribbble.py
social_core/backends/drip.py
social_core/backends/dropbox.py
social_core/backends/echosign.py
social_core/backends/edmodo.py
social_core/backends/email.py
social_core/backends/eventbrite.py
social_core/backends/eveonline.py
social_core/backends/evernote.py
social_core/backends/exacttarget.py
social_core/backends/facebook.py
social_core/backends/fedora.py
social_core/backends/fitbit.py
social_core/backends/five_hundred_px.py
social_core/backends/flickr.py
social_core/backends/foursquare.py
social_core/backends/gae.py
social_core/backends/github.py
social_core/backends/github_enterprise.py
social_core/backends/gitlab.py
social_core/backends/goclio.py
social_core/backends/goclioeu.py
social_core/backends/google.py
social_core/backends/google_openidconnect.py
social_core/backends/instagram.py
social_core_optimized-0.0.1.dist-info/LICENSE
social_core_optimized-0.0.1.dist-info/METADATA
social_core_optimized-0.0.1.dist-info/WHEEL
social_core_optimized-0.0.1.dist-info/top_level.txt
social_core_optimized-0.0.1.dist-info/RECORD
