Metadata-Version: 2.1
Name: social-core-optimized
Version: 0.0.1
Summary: A optimization of social_django_auth
Home-page: https://github.com/marciojunior/social-core-optimized
Author: Marcio Alfredo
Author-email: marcio.alfredo1@gmail.com
License: UNKNOWN
Platform: UNKNOWN
Classifier: Programming Language :: Python :: 3
Classifier: License :: OSI Approved :: BSD License
Classifier: Operating System :: OS Independent
